ttkbootstrap_icons_fluent_reg/__init__.py
ttkbootstrap_icons_fluent_reg/glyphmap.json
ttkbootstrap_icons_fluent_reg/icon.py
ttkbootstrap_icons_fluent_reg/provider.py
ttkbootstrap_icons_fluent_reg/LICENSES/MIT.txt
ttkbootstrap_icons_fluent_reg/fonts/FluentSystemIcons-Regular.ttf
ttkbootstrap_icons_fluent_reg-1.0.0.dist-info/METADATA
ttkbootstrap_icons_fluent_reg-1.0.0.dist-info/WHEEL
ttkbootstrap_icons_fluent_reg-1.0.0.dist-info/entry_points.txt
ttkbootstrap_icons_fluent_reg-1.0.0.dist-info/top_level.txt
ttkbootstrap_icons_fluent_reg-1.0.0.dist-info/RECORD
