Metadata-Version: 2.4
Name: ttkbootstrap-icons-fluent-reg
Version: 1.0.0
Summary: Fluent System Icons Regular (font-based) provider for ttkbootstrap-icons
Author: Israel Dryer
License-Expression: MIT
Project-URL: Homepage, https://github.com/israel-dryer/ttkbootstrap-icons
Requires-Python: >=3.10
Requires-Dist: Pillow>=9.1
Requires-Dist: ttkbootstrap-icons>=4.0.0
